codetags/__init__.py
codetags/main.py
codetags/misc.py
codetags/util.py
codetags-0.1.1.dist-info/LICENSE.txt
codetags-0.1.1.dist-info/METADATA
codetags-0.1.1.dist-info/WHEEL
codetags-0.1.1.dist-info/top_level.txt
codetags-0.1.1.dist-info/RECORD
